course_search/VERSION
course_search/__init__.py
course_search/course_search.py
course_search/params.yaml
course_search/utils.py
course_search/config/__init__.py
course_search/config/core.py
ssg_ada_course_search-0.0.4.dist-info/METADATA
ssg_ada_course_search-0.0.4.dist-info/WHEEL
ssg_ada_course_search-0.0.4.dist-info/top_level.txt
ssg_ada_course_search-0.0.4.dist-info/RECORD
